zrtool/__init__.py
zrtool/__main__.py
zrtool/cli.py
zrtool/tool.py
zrtool/zrpa.py
zrtool-0.2.0.dist-info/entry_points.txt
zrtool-0.2.0.dist-info/LICENSE
zrtool-0.2.0.dist-info/WHEEL
zrtool-0.2.0.dist-info/METADATA
zrtool-0.2.0.dist-info/RECORD
