Metadata-Version: 2.1
Name: zrtool
Version: 0.2.0
Summary: CLI tool to deal with ZoomR16 project
Home-page: https://gitlab.com/remytms/zrtool
License: GPL-3.0-or-later
Keywords: cli,zoomr16,audio,recorder
Author: Rémy Taymans
Author-email: remytms@tsmail.eu
Requires-Python: >=3.6,<4.0
Classifier: Development Status :: 3 - Alpha
Classifier: Intended Audience :: End Users/Desktop
Classifier: License :: OSI Approved :: GNU General Public License v3 or later (GPLv3+)
Classifier: Operating System :: POSIX
Classifier: Operating System :: Unix
Classifier: Programming Language :: Python :: 3
Classifier: Programming Language :: Python :: 3.6
Classifier: Programming Language :: Python :: 3.7
Classifier: Programming Language :: Python :: 3.8
Classifier: Programming Language :: Python :: 3.9
Classifier: Programming Language :: Python :: Implementation :: CPython
Classifier: Topic :: Multimedia :: Sound/Audio
Requires-Dist: PyYAML (>=5.3,<6.0)
Requires-Dist: click (>=7.0,<8.0)
Requires-Dist: invoke (>=1.3,<2.0)
Project-URL: Repository, https://gitlab.com/remytms/zrtool
